{
  "project_info": {
    "project_number": "1097550903854",
    "firebase_url": "https://hoocons-44adb.firebaseio.com",
    "project_id": "hoocons-44adb",
    "storage_bucket": "hoocons-44adb.appspot.com"
  },
  "client": [
    {
      "client_info": {
        "mobilesdk_app_id": "1:1097550903854:android:1e179414d5eedb8c",
        "android_client_info": {
          "package_name": "com.hoocons.hoocons_android"
        }
      },
      "oauth_client": [
        {
          "client_id": "1097550903854-1ib4bk2ftvvb9ht5jg22j6bmiqu88b39.apps.googleusercontent.com",
          "client_type": 3
        }
      ],
      "api_key": [
        {
          "current_key": "AIzaSyBZmoJOONuX2RuXo86WGrqOqBxU_Xx_j_U"
        }
      ],
      "services": {
        "analytics_service": {
          "status": 1
        },
        "appinvite_service": {
          "status": 1,
          "other_platform_oauth_client": []
        },
        "ads_service": {
          "status": 2
        }
      }
    }
  ],
  "configuration_version": "1"
}